pyobs_pilar/__init__.py
pyobs_pilar/pilardriver.py
pyobs_pilar/pilarerror.py
pyobs_pilar/pilartelescope.py
pyobs_pilar-1.6.0.dist-info/METADATA
pyobs_pilar-1.6.0.dist-info/WHEEL
pyobs_pilar-1.6.0.dist-info/licenses/LICENSE
pyobs_pilar-1.6.0.dist-info/RECORD
