Metadata-Version: 2.4
Name: pyobs-pilar
Version: 1.6.0
Summary: pyobs module for Pilar TCS
Author-email: Tim-Oliver Husser <thusser@uni-goettingen.de>
License-Expression: MIT
License-File: LICENSE
Requires-Python: >=3.11
Requires-Dist: astropy<8,>=7.0.1
Requires-Dist: pyobs-core<2,>=1
